[
    {
        "password": "RZLIMYLIKWVZ",
        "length": 12,
        "timestamp": "2025-04-30T13:51:38.872853",
        "user": {
            "id": 1358900071931842601,
            "name": "mero05377",
            "mention": "<@1358900071931842601>"
        }
    },
    {
        "password": "KLWNXKWGMQPZ",
        "length": 12,
        "timestamp": "2025-04-30T13:52:08.970308",
        "user": {
            "id": 1358900071931842601,
            "name": "mero05377",
            "mention": "<@1358900071931842601>"
        }
    },
    {
        "password": "XXTYNNZVGKBC",
        "length": 12,
        "timestamp": "2025-04-30T13:58:12.305634",
        "user": {
            "id": 1358900071931842601,
            "name": "mero05377",
            "mention": "<@1358900071931842601>"
        }
    },
    {
        "password": "WDCGOIYIJSAD",
        "length": 12,
        "timestamp": "2025-04-30T13:59:07.179433",
        "user": {
            "id": 1358900071931842601,
            "name": "mero05377",
            "mention": "<@1358900071931842601>"
        }
    },
    {
        "password": "ZHWIZHALLZZI",
        "length": 12,
        "timestamp": "2025-04-30T14:09:45.635720",
        "user": {
            "id": 1358900071931842601,
            "name": "mero05377",
            "mention": "<@1358900071931842601>"
        }
    },
    {
        "password": "ZSHMCSMWLHPW",
        "length": 12,
        "timestamp": "2025-04-30T14:10:14.339035",
        "user": {
            "id": 1366770877097578526,
            "name": "ツムスクリプト",
            "mention": "<@1366770877097578526>"
        }
    },
    {
        "password": "SMPUYRWKCRZT",
        "length": 12,
        "timestamp": "2025-04-30T14:15:15.825362",
        "user": {
            "id": 1358900071931842601,
            "name": "mero05377",
            "mention": "<@1358900071931842601>"
        }
    },
    {
        "password": "SYIMXDCKNEWT",
        "length": 12,
        "timestamp": "2025-04-30T14:15:38.664838",
        "user": {
            "id": 1358900071931842601,
            "name": "mero05377",
            "mention": "<@1358900071931842601>"
        }
    },
    {
        "password": "PBTLRNGKENWI",
        "length": 12,
        "timestamp": "2025-04-30T14:18:37.605288",
        "user": {
            "id": 1358900071931842601,
            "name": "mero05377",
            "mention": "<@1358900071931842601>"
        }
    },
    {
        "password": "IDVYPZBSETJF",
        "length": 12,
        "timestamp": "2025-04-30T14:19:36.861283",
        "user": {
            "id": 1366770877097578526,
            "name": "ツムスクリプト",
            "mention": "<@1366770877097578526>"
        }
    },
    {
        "password": "SQWAJMCTYLAA",
        "length": 12,
        "timestamp": "2025-04-30T14:20:34.076438",
        "user": {
            "id": 1366770877097578526,
            "name": "ツムスクリプト",
            "mention": "<@1366770877097578526>"
        }
    },
    {
        "password": "VJINQDGPNJLS",
        "length": 12,
        "timestamp": "2025-04-30T14:20:56.886346",
        "user": {
            "id": 1366770877097578526,
            "name": "ツムスクリプト",
            "mention": "<@1366770877097578526>"
        }
    },
    {
        "password": "GZXGHURTTBRC",
        "length": 12,
        "timestamp": "2025-04-30T14:23:36.371723",
        "user": {
            "id": 1358900071931842601,
            "name": "mero05377",
            "mention": "<@1358900071931842601>"
        }
    },
    {
        "password": "OWKNPRPAOXTK",
        "length": 12,
        "timestamp": "2025-04-30T14:28:31.900502",
        "user": {
            "id": 1366770877097578526,
            "name": "ツムスクリプト",
            "mention": "<@1366770877097578526>"
        }
    },
    {
        "password": "ELURBYBGLHSW",
        "length": 12,
        "timestamp": "2025-04-30T14:31:38.630355",
        "user": {
            "id": 1366770877097578526,
            "name": "ツムスクリプト",
            "mention": "<@1366770877097578526>"
        }
    },
    {
        "password": "TIOXHUYSCIMN",
        "length": 12,
        "timestamp": "2025-04-30T14:37:54.883655",
        "user": {
            "id": 1366770877097578526,
            "name": "ツムスクリプト",
            "mention": "<@1366770877097578526>"
        }
    },
    {
        "password": "HPQLWJOQOIDD",
        "length": 12,
        "timestamp": "2025-04-30T14:39:35.138429",
        "user": {
            "id": 1358900071931842601,
            "name": "mero05377",
            "mention": "<@1358900071931842601>"
        }
    },
    {
        "password": "DJSXGVXIUQKN",
        "length": 12,
        "timestamp": "2025-04-30T14:46:28.336814",
        "user": {
            "id": 1366770877097578526,
            "name": "ツムスクリプト",
            "mention": "<@1366770877097578526>"
        }
    },
    {
        "password": "FUXRKMMGSRKA",
        "length": 12,
        "timestamp": "2025-04-30T14:46:55.450473",
        "user": {
            "id": 1366770877097578526,
            "name": "ツムスクリプト",
            "mention": "<@1366770877097578526>"
        }
    },
    {
        "password": "DCSARVFERCNU",
        "length": 12,
        "timestamp": "2025-04-30T14:47:14.579515",
        "user": {
            "id": 1366770877097578526,
            "name": "ツムスクリプト",
            "mention": "<@1366770877097578526>"
        }
    },
    {
        "password": "TQXJSTMIIOCE",
        "length": 12,
        "timestamp": "2025-04-30T14:47:49.548500",
        "user": {
            "id": 1366770877097578526,
            "name": "ツムスクリプト",
            "mention": "<@1366770877097578526>"
        }
    },
    {
        "password": "BDWAEYECSQWW",
        "length": 12,
        "timestamp": "2025-04-30T14:48:18.818979",
        "user": {
            "id": 1366770877097578526,
            "name": "ツムスクリプト",
            "mention": "<@1366770877097578526>"
        }
    },
    {
        "password": "WZJQVURJJPCK",
        "length": 12,
        "timestamp": "2025-04-30T14:51:49.725935",
        "user": {
            "id": 1366770877097578526,
            "name": "ツムスクリプト",
            "mention": "<@1366770877097578526>"
        }
    },
    {
        "password": "WODRBQCDPHXB",
        "length": 12,
        "timestamp": "2025-04-30T14:58:45.295765",
        "user": {
            "id": 1366770877097578526,
            "name": "ツムスクリプト",
            "mention": "<@1366770877097578526>"
        }
    },
    {
        "password": "WZSXGNNWHKWC",
        "length": 12,
        "timestamp": "2025-04-30T14:59:08.644083",
        "user": {
            "id": 1366770877097578526,
            "name": "ツムスクリプト",
            "mention": "<@1366770877097578526>"
        }
    },
    {
        "password": "QNLUBHCNHJOE",
        "length": 12,
        "timestamp": "2025-04-30T14:59:32.975936",
        "user": {
            "id": 1366770877097578526,
            "name": "ツムスクリプト",
            "mention": "<@1366770877097578526>"
        }
    },
    {
        "password": "URCSAQWEBCON",
        "length": 12,
        "timestamp": "2025-04-30T15:02:09.673001",
        "user": {
            "id": 1366770877097578526,
            "name": "ツムスクリプト",
            "mention": "<@1366770877097578526>"
        }
    },
    {
        "password": "ZACAAGQZKXXL",
        "length": 12,
        "timestamp": "2025-04-30T15:03:19.098763",
        "user": {
            "id": 1366770877097578526,
            "name": "ツムスクリプト",
            "mention": "<@1366770877097578526>"
        }
    },
    {
        "password": "MQWRIIJNBFLX",
        "length": 12,
        "timestamp": "2025-04-30T15:03:39.618236",
        "user": {
            "id": 1366770877097578526,
            "name": "ツムスクリプト",
            "mention": "<@1366770877097578526>"
        }
    },
    {
        "password": "CPGJHKFZKZJU",
        "length": 12,
        "timestamp": "2025-04-30T15:04:10.986971",
        "user": {
            "id": 1366770877097578526,
            "name": "ツムスクリプト",
            "mention": "<@1366770877097578526>"
        }
    }
]